odoo/addons/base_global_discount/README.rst
odoo/addons/base_global_discount/__init__.py
odoo/addons/base_global_discount/__manifest__.py
odoo/addons/base_global_discount/i18n/base_global_discount.pot
odoo/addons/base_global_discount/i18n/es.po
odoo/addons/base_global_discount/models/__init__.py
odoo/addons/base_global_discount/models/global_discount.py
odoo/addons/base_global_discount/models/res_partner.py
odoo/addons/base_global_discount/readme/CONFIGURE.rst
odoo/addons/base_global_discount/readme/CONTRIBUTORS.rst
odoo/addons/base_global_discount/readme/DESCRIPTION.rst
odoo/addons/base_global_discount/readme/USAGE.rst
odoo/addons/base_global_discount/security/ir.model.access.csv
odoo/addons/base_global_discount/security/security.xml
odoo/addons/base_global_discount/static/description/icon.png
odoo/addons/base_global_discount/static/description/index.html
odoo/addons/base_global_discount/tests/__init__.py
odoo/addons/base_global_discount/tests/test_global_discount.py
odoo/addons/base_global_discount/views/global_discount_views.xml
odoo/addons/base_global_discount/views/res_partner_views.xml
odoo11_addon_base_global_discount-11.0.1.0.0.99.dev3.dist-info/METADATA
odoo11_addon_base_global_discount-11.0.1.0.0.99.dev3.dist-info/WHEEL
odoo11_addon_base_global_discount-11.0.1.0.0.99.dev3.dist-info/top_level.txt
odoo11_addon_base_global_discount-11.0.1.0.0.99.dev3.dist-info/RECORD
